{
    "name": "All Requests",
    "numberOfRequests": {
        "total": 102,
        "ok": 102,
        "ko": 0
    },
    "minResponseTime": {
        "total": 244,
        "ok": 244,
        "ko": 0
    },
    "maxResponseTime": {
        "total": 1426,
        "ok": 1426,
        "ko": 0
    },
    "meanResponseTime": {
        "total": 399,
        "ok": 399,
        "ko": 0
    },
    "standardDeviation": {
        "total": 259,
        "ok": 259,
        "ko": 0
    },
    "percentiles1": {
        "total": 266,
        "ok": 266,
        "ko": 0
    },
    "percentiles2": {
        "total": 299,
        "ok": 299,
        "ko": 0
    },
    "percentiles3": {
        "total": 808,
        "ok": 808,
        "ko": 0
    },
    "percentiles4": {
        "total": 1426,
        "ok": 1426,
        "ko": 0
    },
    "group1": {
    "name": "t < 800 ms",
    "htmlName": "t < 800 ms",
    "count": 94,
    "percentage": 92.15686274509804
},
    "group2": {
    "name": "800 ms <= t < 1200 ms",
    "htmlName": "t >= 800 ms <br> t < 1200 ms",
    "count": 6,
    "percentage": 5.88235294117647
},
    "group3": {
    "name": "t >= 1200 ms",
    "htmlName": "t >= 1200 ms",
    "count": 2,
    "percentage": 1.9607843137254901
},
    "group4": {
    "name": "failed",
    "htmlName": "failed",
    "count": 0,
    "percentage": 0.0
},
    "meanNumberOfRequestsPerSecond": {
        "total": 5.1,
        "ok": 5.1,
        "ko": 0
    }
}